{
  "name": "tj-odd-or-even-checker",
  "version": "0.1.0",
  "summary": "A simple library to check odd or even numbers.",
  "author": null,
  "license": "MIT License\r\n        \r\n        Copyright (c) 2025 Your Name\r\n        \r\n        Permission is hereby granted, free of charge, to any person obtaining a copy\r\n        of this software and associated documentation files (the \"Software\"), to deal\r\n        in the Software without restriction...",
  "home_page": null,
  "download_filename": "tj_odd_or_even_checker-0.1.0.tar.gz",
  "download_time": "2025-12-04T05:22:14.058456",
  "package_url": "https://pypi.org/project/tj-odd-or-even-checker/"
}